localshop/http.py
localshop/urls.py
localshop/wsgi.py
localshop/runner.py
localshop/__init__.py
localshop/settings.py
localshop/views.py
localshop/utils.py
localshop/templates/403.html
localshop/templates/layout.main.html
localshop/templates/404.html
localshop/templates/frontpage.html
localshop/templates/layout.base.html
localshop/templates/500.html
localshop/templates/permissions/cidr_list.html
localshop/templates/permissions/credential_form.html
localshop/templates/permissions/cidr_form.html
localshop/templates/permissions/credential_list.html
localshop/templates/permissions/credential_confirm_delete.html
localshop/templates/permissions/cidr_confirm_delete.html
localshop/templates/packages/simple_package_detail.html
localshop/templates/packages/package_detail.html
localshop/templates/packages/package_list.html
localshop/templates/packages/simple_package_list.html
localshop/templates/userena/signin_form.html
localshop/templates/userena/base_userena.html
localshop/templates/userena/profile_form.html
localshop/templates/userena/password_form.html
localshop/templates/userena/profile_detail.html
localshop/templates/userena/password_complete.html
localshop/templates/partial/_form_field.html
localshop/templatetags/__init__.py
localshop/templatetags/forms.py
localshop/static/jquery-1.7.1.min.js
localshop/static/bootstrap/img/glyphicons-halflings.png
localshop/static/bootstrap/img/glyphicons-halflings-white.png
localshop/static/bootstrap/js/bootstrap.js
localshop/static/bootstrap/js/bootstrap.min.js
localshop/static/bootstrap/css/bootstrap.min.css
localshop/static/bootstrap/css/bootstrap-responsive.min.css
localshop/static/bootstrap/css/bootstrap-responsive.css
localshop/static/bootstrap/css/bootstrap.css
localshop/management/__init__.py
localshop/management/commands/init.py
localshop/management/commands/__init__.py
localshop/management/commands/upgrade.py
localshop/apps/__init__.py
localshop/apps/permissions/models.py
localshop-0.9.3.dist-info/RECORD
localshop-0.9.3.dist-info/METADATA
localshop-0.9.3.dist-info/metadata.json
localshop-0.9.3.dist-info/top_level.txt
localshop-0.9.3.dist-info/WHEEL
localshop-0.9.3.dist-info/entry_points.txt
localshop-0.9.3.dist-info/DESCRIPTION.rst
