Metadata-Version: 2.0
Name: localshop
Version: 0.9.3
Summary: A private pypi server including auto-mirroring of pypi.
Home-page: http://github.com/mvantellingen/localshop
Author: Michael van Tellingen
Author-email: michaelvantellingen@gmail.com
License: BSD
Platform: UNKNOWN
Classifier: Development Status :: 5 - Production/Stable
Classifier: Framework :: Django
Classifier: Intended Audience :: Developers
Classifier: Intended Audience :: System Administrators
Classifier: Operating System :: OS Independent
Classifier: Topic :: Software Development
Classifier: Topic :: System
Classifier: Topic :: System :: Software Distribution
Classifier: Programming Language :: Python :: 2
Classifier: Programming Language :: Python :: 2.6
Classifier: Programming Language :: Python :: 2.7
Classifier: Programming Language :: Python :: 2 :: Only
Requires-Dist: Django (==1.7.1)
Requires-Dist: Pillow (==2.6.1)
Requires-Dist: celery (==3.1.17)
Requires-Dist: kombu (==3.0.24)
Requires-Dist: django-celery (==3.1.16)
Requires-Dist: django-model-utils (==2.2.0)
Requires-Dist: django-userena (==1.3.1)
Requires-Dist: django-uuidfield (==0.5.0)
Requires-Dist: django-storages (==1.1.8)
Requires-Dist: django-configurations (==0.8)
Requires-Dist: django-environ (==0.3.0)
Requires-Dist: docutils (==0.11)
Requires-Dist: gunicorn (==19.1.1)
Requires-Dist: netaddr (==0.7.12)
Requires-Dist: requests (==2.5.1)
Requires-Dist: Versio (==0.2.1)
